essay_xianyu_mcp_server_lc/__init__.py
essay_xianyu_mcp_server_lc/server.py
essay_xianyu_mcp_server_lc-0.1.7.dist-info/METADATA
essay_xianyu_mcp_server_lc-0.1.7.dist-info/WHEEL
essay_xianyu_mcp_server_lc-0.1.7.dist-info/entry_points.txt
essay_xianyu_mcp_server_lc-0.1.7.dist-info/RECORD
