Metadata-Version: 2.4
Name: essay-xianyu-mcp-server-lc
Version: 0.1.7
Summary: 获取闲鱼相关信息MCP服务
Requires-Python: >=3.11
Requires-Dist: mcp[cli,httpx]>=1.9.0
